pyuptech-0.1.6.5.dist-info/METADATA
pyuptech-0.1.6.5.dist-info/WHEEL
pyuptech/__init__.py
pyuptech/lib/libuptech.so
pyuptech/modules/constant.py
pyuptech/modules/emulation.py
pyuptech/modules/loader.py
pyuptech/modules/logger.py
pyuptech/modules/pins.py
pyuptech/modules/screen.py
pyuptech/modules/sensors.py
pyuptech/tools/display.py
pyuptech-0.1.6.5.dist-info/RECORD
