Metadata-Version: 2.1
Name: pyuptech
Version: 0.1.6.5
Summary: A Python wrapper for the uptech binary lib
Author-Email: Whth <88489697+Whth@users.noreply.github.com>
License: MIT
Requires-Python: >=3.11
Requires-Dist: coloredlogs>=15.0.1
Requires-Dist: terminaltables>=3.1.10
